rag_opt-0.11.1.dist-info/METADATA
rag_opt-0.11.1.dist-info/WHEEL
rag_opt-0.11.1.dist-info/entry_points.txt
rag_opt-0.11.1.dist-info/licenses/LICENCE
rag_opt/__init__.py
rag_opt/_config.py
rag_opt/_manager.py
rag_opt/_prompts.py
rag_opt/_sampler.py
rag_opt/_utils.py
rag_opt/dataset.py
rag_opt/eval/__init__.py
rag_opt/eval/_problem.py
rag_opt/eval/evaluator.py
rag_opt/eval/metrics/__init__.py
rag_opt/eval/metrics/base.py
rag_opt/eval/metrics/full.py
rag_opt/eval/metrics/generation.py
rag_opt/eval/metrics/retrieval.py
rag_opt/llm.py
rag_opt/optimizer.py
rag_opt/rag/__init__.py
rag_opt/rag/_pricing.py
rag_opt/rag/_vectorstore.py
rag_opt/rag/callbacks.py
rag_opt/rag/indexer.py
rag_opt/rag/parser.py
rag_opt/rag/qa.py
rag_opt/rag/rag.py
rag_opt/rag/reranker.py
rag_opt/rag/retriever.py
rag_opt/rag/splitter.py
rag_opt/search_space.py
rag_opt-0.11.1.dist-info/RECORD
