Metadata-Version: 2.1
Name: rag-opt
Version: 0.11.1
Summary: RAG workflow Optimizer based on Bayesian Optimization
Author-Email: abdelrahman abounida <abdelrahmanaboneda@gmail.com>
License: MIT
Requires-Python: <3.13,>=3.11
Requires-Dist: langchain-community>=0.3.21
Requires-Dist: langchain>=0.3.27
Requires-Dist: unstructured>=0.18.14
Requires-Dist: loguru>=0.7.3
Requires-Dist: langchain-text-splitters>=0.3.11
Requires-Dist: tiktoken>=0.11.0
Requires-Dist: qdrant-client>=1.12.1
Requires-Dist: langchain-chroma>=0.2.2
Requires-Dist: faiss-cpu>=1.11.0.post1
Requires-Dist: numpy>=1.26.4
Requires-Dist: langchain-qdrant>=0.2.0
Requires-Dist: flashrank>=0.2.10
Requires-Dist: rank-bm25>=0.2.2
Requires-Dist: fastmobo==0.1.8
Requires-Dist: langsmith>=0.3.45
Requires-Dist: langchain-unstructured>=0.1.6
Requires-Dist: langchain-core>=0.3.76
Requires-Dist: openai>=1.107.2
Requires-Dist: aiohttp>=3.12.15
Requires-Dist: msoffcrypto-tool>=5.4.2
Requires-Dist: langchain-openai>=0.3.34
Requires-Dist: ragatouille>=0.0.9.post2
Requires-Dist: pinecone>=7.3.0
Requires-Dist: langchain-pinecone>=0.2.12
Requires-Dist: pinecone-client>=6.0.0
